django_edelweiss_data/usermanager/__init__.py
django_edelweiss_data/usermanager/admin.py
django_edelweiss_data/usermanager/apps.py
django_edelweiss_data/usermanager/models.py
django_edelweiss_data/usermanager/router.py
django_edelweiss_data_usermanager-0.0.3.dist-info/WHEEL
django_edelweiss_data_usermanager-0.0.3.dist-info/METADATA
django_edelweiss_data_usermanager-0.0.3.dist-info/RECORD
