Metadata-Version: 2.1
Name: django-edelweiss-data-usermanager
Version: 0.0.3
Summary: User management django application for Edelweiss Data
License: MIT
Author: Edelweiss Connect
Author-email: info@edelweissconnect.com
Requires-Python: >=3.6,<4.0
Classifier: License :: OSI Approved :: MIT License
Classifier: Programming Language :: Python :: 3
Classifier: Programming Language :: Python :: 3.6
Classifier: Programming Language :: Python :: 3.7
Classifier: Programming Language :: Python :: 3.8
Requires-Dist: Django (>=2.2,<4.0)
